meson_python_sources_fixer.py
meson_python_sources_fixer-1.0.dist-info/licenses/LICENSE
meson_python_sources_fixer-1.0.dist-info/METADATA
meson_python_sources_fixer-1.0.dist-info/WHEEL
meson_python_sources_fixer-1.0.dist-info/entry_points.txt
meson_python_sources_fixer-1.0.dist-info/top_level.txt
meson_python_sources_fixer-1.0.dist-info/RECORD
