Metadata-Version: 2.4
Name: meson-python-sources-fixer
Version: 1.0
Summary: Linter to list all Python sources in meson.build
Author-email: Omar Sandoval <osandov@osandov.com>
License-Expression: MIT
Project-URL: Homepage, https://github.com/osandov/meson-python-sources-fixer
Project-URL: Issues, https://github.com/osandov/meson-python-sources-fixer/issues
Requires-Python: >=3.8
License-File: LICENSE
Requires-Dist: regex
Provides-Extra: test
Requires-Dist: pyfakefs; extra == "test"
Dynamic: license-file
